astrolabel/__init__.py
astrolabel/data/astrolabel.yml
astrolabel/main.py
astrolabel/tests/__init__.py
astrolabel/tests/test_main.py
astrolabel-0.2.0.dist-info/LICENSE.txt
astrolabel-0.2.0.dist-info/METADATA
astrolabel-0.2.0.dist-info/WHEEL
astrolabel-0.2.0.dist-info/RECORD
