Metadata-Version: 2.1
Name: astrolabel
Version: 0.2.0
Summary: A lightweight Python package for managing astronomy plot labels
Home-page: https://github.com/ivkram/astrolabel
License: MIT
Author: Ivan Kramarenko
Author-email: im.kramarenko@gmail.com
Requires-Python: >=3.9
Classifier: License :: OSI Approved :: MIT License
Classifier: Programming Language :: Python :: 3
Classifier: Programming Language :: Python :: 3.9
Classifier: Programming Language :: Python :: 3.10
Classifier: Programming Language :: Python :: 3.11
Classifier: Programming Language :: Python :: 3.12
Classifier: Programming Language :: Python :: 3.13
Requires-Dist: astropy (>=6.0)
Requires-Dist: dacite (>=1.8.0)
Project-URL: Repository, https://github.com/ivkram/astrolabel
